calc_with_mem/__init__.py
calc_with_mem/calc_with_mem.py
calc_with_mem-0.8.dist-info/LICENSE
calc_with_mem-0.8.dist-info/WHEEL
calc_with_mem-0.8.dist-info/METADATA
calc_with_mem-0.8.dist-info/RECORD
