Metadata-Version: 2.1
Name: calc_with_mem
Version: 0.8
Summary: Package of a calculator using an internal memory
Author-email: Kestutis Gadeikis <kestutis.gadeikis@gmail.com>
Classifier: License :: OSI Approved :: MIT License
